alfano/__init__.py
alfano/controls/GenerateControlTable.py
alfano/controls/YawAngles.py
alfano/controls/__init__.py
alfano/utilities/AlfanoLib.py
alfano/utilities/__init__.py
alfano-0.5b2.dist-info/LICENSE
alfano-0.5b2.dist-info/METADATA
alfano-0.5b2.dist-info/WHEEL
alfano-0.5b2.dist-info/top_level.txt
alfano-0.5b2.dist-info/RECORD
