Metadata-Version: 2.1
Name: alfano
Version: 0.5b2
Summary: Edelbaum-Alfano Low-Thrust Trajectories
Home-page: https://github.com/a093130/Alfano
Author: Colin Helms
Author-email: colinhelms@outlook.com
Classifier: Development Status :: 4 - Beta
Classifier: Environment :: Console
Classifier: Environment :: Plugins
Classifier: Intended Audience :: Science/Research
Classifier: Operating System :: Microsoft :: Windows :: Windows 10
Classifier: Programming Language :: Python :: 3.7
Classifier: License :: OSI Approved :: GNU General Public License v3 (GPLv3)
Classifier: Topic :: Scientific/Engineering :: Mathematics
Requires-Python: >=3.4
License-File: LICENSE
